{"meta": {"code": 200, "requestId": "5e1972daaba297001c991a75"}, "response": {"headerLocation": "Scarborough Village", "headerFullLocation": "Scarborough Village, Toronto", "headerLocationGranularity": "neighborhood", "totalResults": 30, "suggestedBounds": {"ne": {"lat": 43.77444461087202, "lng": -79.17368559359517}, "sw": {"lat": 43.75270058912799, "lng": -79.20373740640483}}, "groups": [{"type": "Recommended Places", "name": "recommended", "items": [{"reasons": {"count": 0, "items": [{"summary": "This spot is popular", "type": "general", "reasonName": "globalInteractionReason"}]}, "venue": {"id": "4bc366dab492d13a51b2a860", "name": "Chick-N-Joy", "location": {"address": "4449 Kingston Road", "crossStreet": "at Lawrence and Morningside", "lat": 43.76875171771289, "lng": -79.18798174616069, "labeledLatLngs": [{"label": "display", "lat": 43.76875171771289, "lng": -79.18798174616069}], "distance": 579, "postalCode": "M1E 2N7", "cc": "CA", "city": "Scarborough", "state": "ON", "country": "Canada", "formattedAddress": ["4449 Kingston Road (at Lawrence and Morningside)", "Scarborough ON M1E 2N7", "Canada"]}, "categories": [{"id": "4d4ae6fc7a7b7dea34424761", "name": "Fried Chicken Joint", "pluralName": "Fried Chicken Joints", "shortName": "Fried Chicken", "icon": {"prefix": "https://ss3.4sqi.net/img/categories_v2/food/friedchicken_", "suffix": ".png"}, "primary": true}], "photos": {"count": 0, "groups": []}}, "referralId": "e-0-4bc366dab492d13a51b2a860-0"}, {"reasons": {"count": 0, "items": [{"summary": "This spot is popular", "type": "general", "reasonName": "globalInteractionReason"}]}, "venue": {"id": "4b3a9504f964a520646a25e3", "name": "LCBO", "location": {"address": "4525 Kingston Rd.", "crossStreet": "at Lawrence Ave. E", "lat": 43.77146181777272, "lng": -79.18438374996185, "labeledLatLngs": [{"label": "display", "lat": 43.77146181777272, "lng": -79.18438374996185}], "distance": 944, "postalCode": "M1E 2P1", "cc": "CA", "city": "Toronto", "state": "ON", "country": "Canada", "formattedAddress": ["4525 Kingston Rd. (at Lawrence Ave. E)", "Toronto ON M1E 2P1", "Canada"]}, "categories": [{"id": "4bf58dd8d48988d186941735", "name": "Liquor Store", "pluralName": "Liquor Stores", "shortName": "Liquor Store", "icon": {"prefix": "https://ss3.4sqi.net/img/categories_v2/shops/food_liquor_", "suffix": ".png"}, "primary": true}], "photos": {"count": 0, "groups": []}}, "referralId": "e-0-4b3a9504f964a520646a25e3-1"}, {"reasons": {"count": 0, "items": [{"summary": "This spot is popular", "type": "general", "reasonName": "globalInteractionReason"}]}, "venue": {"id": "4ba164fdf964a52039b337e3", "name": "Bulk Barn", "location": {"address": "4525 Kingston Rd", "crossStreet": "Morningside Crossing", "lat": 43.77134173380578, "lng": -79.1843408346176, "labeledLatLngs": [{"label": "display", "lat": 43.77134173380578, "lng": -79.1843408346176}], "distance": 933, "cc": "CA", "city": "West Hill", "state": "ON", "country": "Canada", "formattedAddress": ["4525 Kingston Rd (Morningside Crossing)", "West Hill ON", "Canada"]}, "categories": [{"id": "4bf58dd8d48988d1f9941735", "name": "Food & Drink Shop", "pluralName": "Food & Drink Shops", "shortName": "Food & Drink", "icon": {"prefix": "https://ss3.4sqi.net/img/categories_v2/shops/foodanddrink_", "suffix": ".png"}, "primary": true}], "photos": {"count": 0, "groups": []}}, "referralId": "e-0-4ba164fdf964a52039b337e3-2"}, {"reasons": {"count": 0, "items": [{"summary": "This spot is popular", "type": "general", "reasonName": "globalInteractionReason"}]}, "venue": {"id": "4b6074e3f964a5200fe729e3", "name": "Swiss Chalet Rotisserie & Grill", "location": {"address": "4410 Kingston Rd", "lat": 43.76769708292701, "lng": -79.1899135003439, "labeledLatLngs": [{"label": "display", "lat": 43.76769708292701, "lng": -79.1899135003439}], "distance": 469, "postalCode": "M1E 2N5", "cc": "CA", "city": "Scarborough", "state": "ON", "country": "Canada", "formattedAddress": ["4410 Kingston Rd", "Scarborough ON M1E 2N5", "Canada"]}, "categories": [{"id": "4bf58dd8d48988d1ca941735", "name": "Pizza Place", "pluralName": "Pizza Places", "shortName": "Pizza", "icon": {"prefix": "https://ss3.4sqi.net/img/categories_v2/food/pizza_", "suffix": ".png"}, "primary": true}], "photos": {"count": 0, "groups": []}}, "referralId": "e-0-4b6074e3f964a5200fe729e3-3"}, {"reasons": {"count": 0, "items": [{"summary": "This spot is popular", "type": "general", "reasonName": "globalInteractionReason"}]}, "venue": {"id": "4c9fdb04542b224bca4201a0", "name": "Little Caesars Pizza", "location": {"address": "4218 Lawrence Avenue East", "lat": 43.76904597684398, "lng": -79.18438601716002, "labeledLatLngs": [{"label": "display", "lat": 43.76904597684398, "lng": -79.18438601716002}], "distance": 701, "postalCode": "M1E 4X9", "cc": "CA", "city": "Scarborough", "state": "ON", "country": "Canada", "formattedAddress": ["4218 Lawrence Avenue East", "Scarborough ON M1E 4X9", "Canada"]}, "categories": [{"id": "4bf58dd8d48988d1ca941735", "name": "Pizza Place", "pluralName": "Pizza Places", "shortName": "Pizza", "icon": {"prefix": "https://ss3.4sqi.net/img/categories_v2/food/pizza_", "suffix": ".png"}, "primary": true}], "photos": {"count": 0, "groups": []}}, "referralId": "e-0-4c9fdb04542b224bca4201a0-4"}, {"reasons": {"count": 0, "items": [{"summary": "This spot is popular", "type": "general", "reasonName": "globalInteractionReason"}]}, "venue": {"id": "4beca2f9d6e676b0538764d4", "name": "Booster Juice", "location": {"address": "4525 Kingston Road, Unit #H8", "crossStreet": "at Collinsgrove Rd.", "lat": 43.77066813, "lng": -79.18415042, "labeledLatLngs": [{"label": "display", "lat": 43.77066813, "lng": -79.18415042}], "distance": 870, "postalCode": "M1E 2P1", "cc": "CA", "city": "Scarborough", "state": "ON", "country": "Canada", "formattedAddress": ["4525 Kingston Road, Unit #H8 (at Collinsgrove Rd.)", "Scarborough ON M1E 2P1", "Canada"]}, "categories": [{"id": "52f2ab2ebcbc57f1066b8b41", "name": "Smoothie Shop", "pluralName": "Smoothie Shops", "shortName": "Smoothie Shop", "icon": {"prefix": "https://ss3.4sqi.net/img/categories_v2/food/juicebar_", "suffix": ".png"}, "primary": true}], "photos": {"count": 0, "groups": []}}, "referralId": "e-0-4beca2f9d6e676b0538764d4-5"}, {"reasons": {"count": 0, "items": [{"summary": "This spot is popular", "type": "general", "reasonName": "globalInteractionReason"}]}, "venue": {"id": "510bd6f1e4b0256d6cc14409", "name": "Sunset Grill", "location": {"address": "4551 Kingston Rd.", "crossStreet": "Lawrence", "lat": 43.77231854994461, "lng": -79.18490011736371, "labeledLatLngs": [{"label": "display", "lat": 43.77231854994461, "lng": -79.18490011736371}], "distance": 1020, "postalCode": "4551 Kingsto", "cc": "CA", "city": "Toronto", "state": "ON", "country": "Canada", "formattedAddress": ["4551 Kingston Rd. (Lawrence)", "Toronto ON 4551 Kingsto", "Canada"]}, "categories": [{"id": "4bf58dd8d48988d143941735", "name": "Breakfast Spot", "pluralName": "Breakfast Spots", "shortName": "Breakfast", "icon": {"prefix": "https://ss3.4sqi.net/img/categories_v2/food/breakfast_", "suffix": ".png"}, "primary": true}], "photos": {"count": 0, "groups": []}}, "referralId": "e-0-510bd6f1e4b0256d6cc14409-6"}, {"reasons": {"count": 0, "items": [{"summary": "This spot is popular", "type": "general", "reasonName": "globalInteractionReason"}]}, "venue": {"id": "4bdcd893462b2d7f13a3113c", "name": "The Beer Store", "location": {"address": "4479 Kingston Rd Unit 1", "crossStreet": "btw Morningside & Lawrence", "lat": 43.769793, "lng": -79.1875054, "labeledLatLngs": [{"label": "display", "lat": 43.769793, "lng": -79.1875054}], "distance": 699, "postalCode": "M1E 2N7", "cc": "CA", "city": "Scarborough", "state": "ON", "country": "Canada", "formattedAddress": ["4479 Kingston Rd Unit 1 (btw Morningside & Lawrence)", "Scarborough ON M1E 2N7", "Canada"]}, "categories": [{"id": "5370f356bcbc57f1066c94c2", "name": "Beer Store", "pluralName": "Beer Stores", "shortName": "Beer Store", "icon": {"prefix": "https://ss3.4sqi.net/img/categories_v2/nightlife/beergarden_", "suffix": ".png"}, "primary": true}], "photos": {"count": 0, "groups": []}}, "referralId": "e-0-4bdcd893462b2d7f13a3113c-7"}, {"reasons": {"count": 0, "items": [{"summary": "This spot is popular", "type": "general", "reasonName": "globalInteractionReason"}]}, "venue": {"id": "4b9ebe82f964a5206efe36e3", "name": "Shoeless Joe's", "location": {"address": "245 Morningside Ave", "crossStreet": "Lawrence Ave E", "lat": 43.768891580866935, "lng": -79.18585091829299, "labeledLatLngs": [{"label": "display", "lat": 43.768891580866935, "lng": -79.18585091829299}], "distance": 635, "cc": "CA", "city": "Scarborough", "state": "ON", "country": "Canada", "formattedAddress": ["245 Morningside Ave (Lawrence Ave E)", "Scarborough ON", "Canada"]}, "categories": [{"id": "4bf58dd8d48988d11d941735", "name": "Sports Bar", "pluralName": "Sports Bars", "shortName": "Sports Bar", "icon": {"prefix": "https://ss3.4sqi.net/img/categories_v2/nightlife/sportsbar_", "suffix": ".png"}, "primary": true}], "photos": {"count": 0, "groups": []}}, "referralId": "e-0-4b9ebe82f964a5206efe36e3-8"}, {"reasons": {"count": 0, "items": [{"summary": "This spot is popular", "type": "general", "reasonName": "globalInteractionReason"}]}, "venue": {"id": "4b75e7bbf964a520992d2ee3", "name": "Shoppers Drug Mart", "location": {"address": "255 Morningside Ave", "crossStreet": "at Kingston Rd.", "lat": 43.770282, "lng": -79.185012, "labeledLatLngs": [{"label": "display", "lat": 43.770282, "lng": -79.185012}], "distance": 803, "postalCode": "M1E 3E6", "cc": "CA", "city": "Scarborough", "state": "ON", "country": "Canada", "formattedAddress": ["255 Morningside Ave (at Kingston Rd.)", "Scarborough ON M1E 3E6", "Canada"]}, "categories": [{"id": "4bf58dd8d48988d10f951735", "name": "Pharmacy", "pluralName": "Pharmacies", "shortName": "Pharmacy", "icon": {"prefix": "https://ss3.4sqi.net/img/categories_v2/shops/pharmacy_", "suffix": ".png"}, "primary": true}], "photos": {"count": 0, "groups": []}}, "referralId": "e-0-4b75e7bbf964a520992d2ee3-9"}, {"reasons": {"count": 0, "items": [{"summary": "This spot is popular", "type": "general", "reasonName": "globalInteractionReason"}]}, "venue": {"id": "4b06eb1cf964a52005f322e3", "name": "Starbucks", "location": {"address": "255 Morningside Ave", "crossStreet": "Kingston Rd", "lat": 43.77037, "lng": -79.18649, "labeledLatLngs": [{"label": "display", "lat": 43.77037, "lng": -79.18649}], "distance": 777, "postalCode": "M1E 3E6", "cc": "CA", "city": "Toronto", "state": "ON", "country": "Canada", "formattedAddress": ["255 Morningside Ave (Kingston Rd)", "Toronto ON M1E 3E6", "Canada"]}, "categories": [{"id": "4bf58dd8d48988d1e0931735", "name": "Coffee Shop", "pluralName": "Coffee Shops", "shortName": "Coffee Shop", "icon": {"prefix": "https://ss3.4sqi.net/img/categories_v2/food/coffeeshop_", "suffix": ".png"}, "primary": true}], "photos": {"count": 0, "groups": []}}, "referralId": "e-0-4b06eb1cf964a52005f322e3-10"}, {"reasons": {"count": 0, "items": [{"summary": "This spot is popular", "type": "general", "reasonName": "globalInteractionReason"}]}, "venue": {"id": "4b9023e9f964a5200e7833e3", "name": "McDonald's", "location": {"address": "4435 Kingston Rd.", "crossStreet": "Lawrence Ave E", "lat": 43.76833410355284, "lng": -79.18828754919781, "labeledLatLngs": [{"label": "display", "lat": 43.76833410355284, "lng": -79.18828754919781}], "distance": 531, "postalCode": "M1E 2N7", "cc": "CA", "city": "Scarborough", "state": "ON", "country": "Canada", "formattedAddress": ["4435 Kingston Rd. (Lawrence Ave E)", "Scarborough ON M1E 2N7", "Canada"]}, "categories": [{"id": "4bf58dd8d48988d16e941735", "name": "Fast Food Restaurant", "pluralName": "Fast Food Restaurants", "shortName": "Fast Food", "icon": {"prefix": "https://ss3.4sqi.net/img/categories_v2/food/fastfood_", "suffix": ".png"}, "primary": true}], "photos": {"count": 0, "groups": []}}, "referralId": "e-0-4b9023e9f964a5200e7833e3-11"}, {"reasons": {"count": 0, "items": [{"summary": "This spot is popular", "type": "general", "reasonName": "globalInteractionReason"}]}, "venue": {"id": "4cc33d971e596dcbe61ac967", "name": "TD Canada Trust", "location": {"address": "4515 Kingston Rd", "crossStreet": "at Morningside Ave.", "lat": 43.770997118312, "lng": -79.18599759390418, "labeledLatLngs": [{"label": "display", "lat": 43.770997118312, "lng": -79.18599759390418}], "distance": 854, "postalCode": "M1E 2P1", "cc": "CA", "city": "Scarborough", "state": "ON", "country": "Canada", "formattedAddress": ["4515 Kingston Rd (at Morningside Ave.)", "Scarborough ON M1E 2P1", "Canada"]}, "categories": [{"id": "4bf58dd8d48988d10a951735", "name": "Bank", "pluralName": "Banks", "shortName": "Bank", "icon": {"prefix": "https://ss3.4sqi.net/img/categories_v2/shops/financial_", "suffix": ".png"}, "primary": true}], "photos": {"count": 0, "groups": []}}, "referralId": "e-0-4cc33d971e596dcbe61ac967-12"}, {"reasons": {"count": 0, "items": [{"summary": "This spot is popular", "type": "general", "reasonName": "globalInteractionReason"}]}, "venue": {"id": "55198a64498eed3a6b5f76e2", "name": "KFC", "location": {"address": "245 Morningside Avenue", "lat": 43.76898399423786, "lng": -79.1856287262852, "labeledLatLngs": [{"label": "display", "lat": 43.76898399423786, "lng": -79.1856287262852}], "distance": 651, "postalCode": "M1E 3E6", "cc": "CA", "city": "Scarborough", "state": "ON", "country": "Canada", "formattedAddress": ["245 Morningside Avenue", "Scarborough ON M1E 3E6", "Canada"]}, "categories": [{"id": "4bf58dd8d48988d16e941735", "name": "Fast Food Restaurant", "pluralName": "Fast Food Restaurants", "shortName": "Fast Food", "icon": {"prefix": "https://ss3.4sqi.net/img/categories_v2/food/fastfood_", "suffix": ".png"}, "primary": true}], "photos": {"count": 0, "groups": []}}, "referralId": "e-0-55198a64498eed3a6b5f76e2-13"}, {"reasons": {"count": 0, "items": [{"summary": "This spot is popular", "type": "general", "reasonName": "globalInteractionReason"}]}, "venue": {"id": "4bcb5d75937ca593956ba992", "name": "Subway", "location": {"address": "4545 Kingston Rd", "crossStreet": "Morningside Crossing", "lat": 43.771828795899665, "lng": -79.18501631588651, "labeledLatLngs": [{"label": "display", "lat": 43.771828795899665, "lng": -79.18501631588651}], "distance": 965, "postalCode": "M1E 2P1", "cc": "CA", "city": "Toronto", "state": "ON", "country": "Canada", "formattedAddress": ["4545 Kingston Rd (Morningside Crossing)", "Toronto ON M1E 2P1", "Canada"]}, "categories": [{"id": "4bf58dd8d48988d1c5941735", "name": "Sandwich Place", "pluralName": "Sandwich Places", "shortName": "Sandwiches", "icon": {"prefix": "https://ss3.4sqi.net/img/categories_v2/food/deli_", "suffix": ".png"}, "primary": true}], "photos": {"count": 0, "groups": []}}, "referralId": "e-0-4bcb5d75937ca593956ba992-14"}, {"reasons": {"count": 0, "items": [{"summary": "This spot is popular", "type": "general", "reasonName": "globalInteractionReason"}]}, "venue": {"id": "4bd22faacaff9521f94cd2f0", "name": "Dollarama", "location": {"address": "4525 Kingston Rd,Morningside Mall", "crossStreet": "Morningside Crossing", "lat": 43.771085, "lng": -79.184288, "labeledLatLngs": [{"label": "display", "lat": 43.771085, "lng": -79.184288}], "distance": 908, "postalCode": "M1E 2P1", "cc": "CA", "city": "Toronto", "state": "ON", "country": "Canada", "formattedAddress": ["4525 Kingston Rd,Morningside Mall (Morningside Crossing)", "Toronto ON M1E 2P1", "Canada"]}, "categories": [{"id": "52dea92d3cf9994f4e043dbb", "name": "Discount Store", "pluralName": "Discount Stores", "shortName": "Discount Store", "icon": {"prefix": "https://ss3.4sqi.net/img/categories_v2/shops/discountstore_", "suffix": ".png"}, "primary": true}], "photos": {"count": 0, "groups": []}}, "referralId": "e-0-4bd22faacaff9521f94cd2f0-15"}, {"reasons": {"count": 0, "items": [{"summary": "This spot is popular", "type": "general", "reasonName": "globalInteractionReason"}]}, "venue": {"id": "4c83f00d2f1c236a8d704743", "name": "Pizza Hut", "location": {"address": "259 Morningside Ave", "lat": 43.770455, "lng": -79.1861572, "labeledLatLngs": [{"label": "display", "lat": 43.770455, "lng": -79.1861572}], "distance": 793, "postalCode": "M1E 2M9", "cc": "CA", "city": "Scarborough", "state": "ON", "country": "Canada", "formattedAddress": ["259 Morningside Ave", "Scarborough ON M1E 2M9", "Canada"]}, "categories": [{"id": "4bf58dd8d48988d1ca941735", "name": "Pizza Place", "pluralName": "Pizza Places", "shortName": "Pizza", "icon": {"prefix": "https://ss3.4sqi.net/img/categories_v2/food/pizza_", "suffix": ".png"}, "primary": true}], "photos": {"count": 0, "groups": []}}, "referralId": "e-0-4c83f00d2f1c236a8d704743-16"}, {"reasons": {"count": 0, "items": [{"summary": "This spot is popular", "type": "general", "reasonName": "globalInteractionReason"}]}, "venue": {"id": "4c7ee2efd860b60c915d5f9d", "name": "Taste Of Greek Cuisine", "location": {"lat": 43.768259, "lng": -79.189608, "labeledLatLngs": [{"label": "display", "lat": 43.768259, "lng": -79.189608}], "distance": 526, "cc": "CA", "city": "Toronto", "state": "ON", "country": "Canada", "formattedAddress": ["Toronto ON", "Canada"]}, "categories": [{"id": "4bf58dd8d48988d10e941735", "name": "Greek Restaurant", "pluralName": "Greek Restaurants", "shortName": "Greek", "icon": {"prefix": "https://ss3.4sqi.net/img/categories_v2/food/greek_", "suffix": ".png"}, "primary": true}], "photos": {"count": 0, "groups": []}}, "referralId": "e-0-4c7ee2efd860b60c915d5f9d-17"}, {"reasons": {"count": 0, "items": [{"summary": "This spot is popular", "type": "general", "reasonName": "globalInteractionReason"}]}, "venue": {"id": "4c85a8c2ee6fef3b9b123e5c", "name": "Pizza Pizza", "location": {"address": "4447 Kingston Road, Unit 7-8", "lat": 43.7684131598454, "lng": -79.18792963027954, "labeledLatLngs": [{"label": "display", "lat": 43.7684131598454, "lng": -79.18792963027954}], "distance": 542, "postalCode": "M1E 2N7", "cc": "CA", "city": "Scarborough", "state": "ON", "country": "Canada", "formattedAddress": ["4447 Kingston Road, Unit 7-8", "Scarborough ON M1E 2N7", "Canada"]}, "categories": [{"id": "4bf58dd8d48988d1ca941735", "name": "Pizza Place", "pluralName": "Pizza Places", "shortName": "Pizza", "icon": {"prefix": "https://ss3.4sqi.net/img/categories_v2/food/pizza_", "suffix": ".png"}, "primary": true}], "photos": {"count": 0, "groups": []}}, "referralId": "e-0-4c85a8c2ee6fef3b9b123e5c-18"}, {"reasons": {"count": 0, "items": [{"summary": "This spot is popular", "type": "general", "reasonName": "globalInteractionReason"}]}, "venue": {"id": "4b847328f964a520293631e3", "name": "Food Basics", "location": {"address": "255 Morningside Avenue", "crossStreet": "Kingston Rd.", "lat": 43.77001337309147, "lng": -79.18553952416049, "labeledLatLngs": [{"label": "display", "lat": 43.77001337309147, "lng": -79.18553952416049}], "distance": 760, "postalCode": "M1E 3E6", "cc": "CA", "city": "Scarborough", "state": "ON", "country": "Canada", "formattedAddress": ["255 Morningside Avenue (Kingston Rd.)", "Scarborough ON M1E 3E6", "Canada"]}, "categories": [{"id": "52f2ab2ebcbc57f1066b8b46", "name": "Supermarket", "pluralName": "Supermarkets", "shortName": "Supermarket", "icon": {"prefix": "https://ss3.4sqi.net/img/categories_v2/shops/food_grocery_", "suffix": ".png"}, "primary": true}], "photos": {"count": 0, "groups": []}}, "referralId": "e-0-4b847328f964a520293631e3-19"}, {"reasons": {"count": 0, "items": [{"summary": "This spot is popular", "type": "general", "reasonName": "globalInteractionReason"}]}, "venue": {"id": "4bc364c0461576b0dd927e32", "name": "Lick's Homeburgers", "location": {"address": "4543 Kingston Rd.", "crossStreet": "at Morningside Ave.", "lat": 43.77167716068725, "lng": -79.18538033022018, "labeledLatLngs": [{"label": "display", "lat": 43.77167716068725, "lng": -79.18538033022018}], "distance": 941, "cc": "CA", "city": "Toronto", "state": "ON", "country": "Canada", "formattedAddress": ["4543 Kingston Rd. (at Morningside Ave.)", "Toronto ON", "Canada"]}, "categories": [{"id": "4bf58dd8d48988d16c941735", "name": "Burger Joint", "pluralName": "Burger Joints", "shortName": "Burgers", "icon": {"prefix": "https://ss3.4sqi.net/img/categories_v2/food/burger_", "suffix": ".png"}, "primary": true}], "photos": {"count": 0, "groups": []}}, "referralId": "e-0-4bc364c0461576b0dd927e32-20"}, {"reasons": {"count": 0, "items": [{"summary": "This spot is popular", "type": "general", "reasonName": "globalInteractionReason"}]}, "venue": {"id": "513b84e6e4b0ef935943c0ad", "name": "Lawrence Ave E & Kingston Rd", "location": {"address": "Lawrence Ave E & Kingston Rd", "crossStreet": "Lawrence Ave E & Kingston Rd", "lat": 43.767704, "lng": -79.18949, "labeledLatLngs": [{"label": "display", "lat": 43.767704, "lng": -79.18949}], "distance": 464, "postalCode": "M1E", "cc": "CA", "city": "Toronto", "state": "ON", "country": "Canada", "formattedAddress": ["Lawrence Ave E & Kingston Rd (Lawrence Ave E & Kingston Rd)", "Toronto ON M1E", "Canada"]}, "categories": [{"id": "52f2ab2ebcbc57f1066b8b4c", "name": "Intersection", "pluralName": "Intersections", "shortName": "Intersection", "icon": {"prefix": "https://ss3.4sqi.net/img/categories_v2/travel/default_", "suffix": ".png"}, "primary": true}], "photos": {"count": 0, "groups": []}}, "referralId": "e-0-513b84e6e4b0ef935943c0ad-21"}, {"reasons": {"count": 0, "items": [{"summary": "This spot is popular", "type": "general", "reasonName": "globalInteractionReason"}]}, "venue": {"id": "4dea9ff9d4c00071b828d885", "name": "National Thrift", "location": {"address": "4410 Kingston Rd.", "lat": 43.76799932703117, "lng": -79.19024597235247, "labeledLatLngs": [{"label": "display", "lat": 43.76799932703117, "lng": -79.19024597235247}], "distance": 507, "cc": "CA", "city": "Toronto", "state": "ON", "country": "Canada", "formattedAddress": ["4410 Kingston Rd.", "Toronto ON", "Canada"]}, "categories": [{"id": "4bf58dd8d48988d101951735", "name": "Thrift / Vintage Store", "pluralName": "Thrift / Vintage Stores", "shortName": "Thrift / Vintage", "icon": {"prefix": "https://ss3.4sqi.net/img/categories_v2/shops/default_", "suffix": ".png"}, "primary": true}], "photos": {"count": 0, "groups": []}}, "referralId": "e-0-4dea9ff9d4c00071b828d885-22"}, {"reasons": {"count": 0, "items": [{"summary": "This spot is popular", "type": "general", "reasonName": "globalInteractionReason"}]}, "venue": {"id": "4b7c82cff964a520df972fe3", "name": "Tim Hortons", "location": {"address": "4479 Kingston Rd", "crossStreet": "Morningside Avenue", "lat": 43.7698137, "lng": -79.1869756, "labeledLatLngs": [{"label": "display", "lat": 43.7698137, "lng": -79.1869756}], "distance": 708, "postalCode": "M1E 2N7", "cc": "CA", "city": "Scarborough", "state": "ON", "country": "Canada", "formattedAddress": ["4479 Kingston Rd (Morningside Avenue)", "Scarborough ON M1E 2N7", "Canada"]}, "categories": [{"id": "4bf58dd8d48988d1e0931735", "name": "Coffee Shop", "pluralName": "Coffee Shops", "shortName": "Coffee Shop", "icon": {"prefix": "https://ss3.4sqi.net/img/categories_v2/food/coffeeshop_", "suffix": ".png"}, "primary": true}], "photos": {"count": 0, "groups": []}}, "referralId": "e-0-4b7c82cff964a520df972fe3-23"}, {"reasons": {"count": 0, "items": [{"summary": "This spot is popular", "type": "general", "reasonName": "globalInteractionReason"}]}, "venue": {"id": "4b904077f964a520037f33e3", "name": "Rexall", "location": {"address": "4459 Kingston Rd", "crossStreet": "Lawerence Ave E", "lat": 43.768806, "lng": -79.188405, "labeledLatLngs": [{"label": "display", "lat": 43.768806, "lng": -79.188405}], "distance": 583, "postalCode": "M1E 2N7", "cc": "CA", "city": "Scarborough", "state": "ON", "country": "Canada", "formattedAddress": ["4459 Kingston Rd (Lawerence Ave E)", "Scarborough ON M1E 2N7", "Canada"]}, "categories": [{"id": "4bf58dd8d48988d10f951735", "name": "Pharmacy", "pluralName": "Pharmacies", "shortName": "Pharmacy", "icon": {"prefix": "https://ss3.4sqi.net/img/categories_v2/shops/pharmacy_", "suffix": ".png"}, "primary": true}], "photos": {"count": 0, "groups": []}}, "referralId": "e-0-4b904077f964a520037f33e3-24"}, {"reasons": {"count": 0, "items": [{"summary": "This spot is popular", "type": "general", "reasonName": "globalInteractionReason"}]}, "venue": {"id": "4be459f3d4f7c9b602072420", "name": "Joseph's No Frills", "location": {"address": "4473 Kingston Rd", "crossStreet": "at Morningside Ave.", "lat": 43.769591, "lng": -79.187669, "labeledLatLngs": [{"label": "display", "lat": 43.769591, "lng": -79.187669}], "distance": 675, "postalCode": "M1E 2N7", "cc": "CA", "city": "Scarborough", "state": "ON", "country": "Canada", "formattedAddress": ["4473 Kingston Rd (at Morningside Ave.)", "Scarborough ON M1E 2N7", "Canada"]}, "categories": [{"id": "4bf58dd8d48988d118951735", "name": "Grocery Store", "pluralName": "Grocery Stores", "shortName": "Grocery Store", "icon": {"prefix": "https://ss3.4sqi.net/img/categories_v2/shops/food_grocery_", "suffix": ".png"}, "primary": true}], "photos": {"count": 0, "groups": []}}, "referralId": "e-0-4be459f3d4f7c9b602072420-25"}, {"reasons": {"count": 0, "items": [{"summary": "This spot is popular", "type": "general", "reasonName": "globalInteractionReason"}]}, "venue": {"id": "4e3bd3e3483b04e17a7f445f", "name": "Kal Tire", "location": {"address": "4557 Kingston Rd", "lat": 43.772666, "lng": -79.184443, "labeledLatLngs": [{"label": "display", "lat": 43.772666, "lng": -79.184443}], "distance": 1068, "postalCode": "M1E 2P3", "cc": "CA", "city": "Scarborough", "state": "ON", "country": "Canada", "formattedAddress": ["4557 Kingston Rd", "Scarborough ON M1E 2P3", "Canada"]}, "categories": [{"id": "4bf58dd8d48988d124951735", "name": "Automotive Shop", "pluralName": "Automotive Shops", "shortName": "Automotive", "icon": {"prefix": "https://ss3.4sqi.net/img/categories_v2/shops/automotive_", "suffix": ".png"}, "primary": true}], "photos": {"count": 0, "groups": []}}, "referralId": "e-0-4e3bd3e3483b04e17a7f445f-26"}, {"reasons": {"count": 0, "items": [{"summary": "This spot is popular", "type": "general", "reasonName": "globalInteractionReason"}]}, "venue": {"id": "4b114be3f964a520e57923e3", "name": "Heron Park Community Centre", "location": {"address": "292 Manse Rd.", "crossStreet": "at Lawrence Ave. E", "lat": 43.76886695009025, "lng": -79.17695787066756, "labeledLatLngs": [{"label": "display", "lat": 43.76886695009025, "lng": -79.17695787066756}], "distance": 1113, "postalCode": "M1E 3V4", "cc": "CA", "city": "Toronto", "state": "ON", "country": "Canada", "formattedAddress": ["292 Manse Rd. (at Lawrence Ave. E)", "Toronto ON M1E 3V4", "Canada"]}, "categories": [{"id": "4bf58dd8d48988d175941735", "name": "Gym / Fitness Center", "pluralName": "Gyms or Fitness Centers", "shortName": "Gym / Fitness", "icon": {"prefix": "https://ss3.4sqi.net/img/categories_v2/building/gym_", "suffix": ".png"}, "primary": true}], "photos": {"count": 0, "groups": []}}, "referralId": "e-0-4b114be3f964a520e57923e3-27"}, {"reasons": {"count": 0, "items": [{"summary": "This spot is popular", "type": "general", "reasonName": "globalInteractionReason"}]}, "venue": {"id": "4e582aceb61c5534c28c2691", "name": "Heron Park", "location": {"address": "Manse", "crossStreet": "Lawrence", "lat": 43.76932738615917, "lng": -79.17720079421997, "labeledLatLngs": [{"label": "display", "lat": 43.76932738615917, "lng": -79.17720079421997}], "distance": 1125, "cc": "CA", "city": "West Hill", "state": "ON", "country": "Canada", "formattedAddress": ["Manse (Lawrence)", "West Hill ON", "Canada"]}, "categories": [{"id": "4bf58dd8d48988d163941735", "name": "Park", "pluralName": "Parks", "shortName": "Park", "icon": {"prefix": "https://ss3.4sqi.net/img/categories_v2/parks_outdoors/park_", "suffix": ".png"}, "primary": true}], "photos": {"count": 0, "groups": []}}, "referralId": "e-0-4e582aceb61c5534c28c2691-28"}, {"reasons": {"count": 0, "items": [{"summary": "This spot is popular", "type": "general", "reasonName": "globalInteractionReason"}]}, "venue": {"id": "4f0b08240cd6e04819efa1ce", "name": "U-Haul Moving & Storage at Kingston Rd", "location": {"address": "4095 Kingston Rd", "lat": 43.7562070660306, "lng": -79.19909437180013, "labeledLatLngs": [{"label": "display", "lat": 43.7562070660306, "lng": -79.19909437180013}], "distance": 1170, "postalCode": "M1E 2M3", "cc": "CA", "city": "Scarborough", "state": "ON", "country": "Canada", "formattedAddress": ["4095 Kingston Rd", "Scarborough ON M1E 2M3", "Canada"]}, "categories": [{"id": "4f04b1572fb6e1c99f3db0bf", "name": "Storage Facility", "pluralName": "Storage Facilities", "shortName": "Storage", "icon": {"prefix": "https://ss3.4sqi.net/img/categories_v2/shops/storage_", "suffix": ".png"}, "primary": true}], "photos": {"count": 0, "groups": []}}, "referralId": "e-0-4f0b08240cd6e04819efa1ce-29"}]}]}}